[
  {
    "id": 1,
    "name": "Morning Black Forest Loop",
    "type": "Ride",
    "gearId": "bike-001",
    "date": "2024-01-28T07:30:00Z",
    "distance": 45.2,
    "movingTime": 5400,
    "elevation": 680,
    "avgSpeed": 30.1,
    "maxSpeed": 52.4,
    "calories": 1250,
    "kudos": 18,
    "achievementCount": 3
  },
  {
    "id": 2,
    "name": "Evening Commute Home",
    "type": "Ride",
    "gearId": "bike-001",
    "date": "2024-01-27T17:45:00Z",
    "distance": 28.5,
    "movingTime": 3600,
    "elevation": 120,
    "avgSpeed": 28.5,
    "maxSpeed": 45.2,
    "calories": 680,
    "kudos": 5,
    "achievementCount": 0
  },
  {
    "id": 3,
    "name": "Schauinsland Summit Climb",
    "type": "Ride",
    "gearId": "bike-001",
    "date": "2024-01-26T09:00:00Z",
    "distance": 22.0,
    "movingTime": 4200,
    "elevation": 1100,
    "avgSpeed": 18.9,
    "maxSpeed": 68.5,
    "calories": 1450,
    "kudos": 32,
    "achievementCount": 5
  },
  {
    "id": 4,
    "name": "Rhine Valley Flat Stage",
    "type": "Ride",
    "gearId": "bike-001",
    "date": "2024-01-25T06:00:00Z",
    "distance": 85.0,
    "movingTime": 9000,
    "elevation": 180,
    "avgSpeed": 34.0,
    "maxSpeed": 48.3,
    "calories": 2100,
    "kudos": 24,
    "achievementCount": 2
  },
  {
    "id": 5,
    "name": "Gravel Adventure Kaiserstuhl",
    "type": "Ride",
    "gearId": "bike-003",
    "date": "2024-01-21T08:30:00Z",
    "distance": 52.3,
    "movingTime": 6300,
    "elevation": 450,
    "avgSpeed": 29.9,
    "maxSpeed": 55.1,
    "calories": 1380,
    "kudos": 15,
    "achievementCount": 1
  },
  {
    "id": 6,
    "name": "MTB Trail Session",
    "type": "Ride",
    "gearId": "bike-002",
    "date": "2024-01-20T14:00:00Z",
    "distance": 18.0,
    "movingTime": 3000,
    "elevation": 520,
    "avgSpeed": 21.6,
    "maxSpeed": 42.8,
    "calories": 820,
    "kudos": 22,
    "achievementCount": 4
  },
  {
    "id": 7,
    "name": "Weekend Century Ride",
    "type": "Ride",
    "gearId": "bike-001",
    "date": "2024-01-14T07:00:00Z",
    "distance": 112.0,
    "movingTime": 13200,
    "elevation": 890,
    "avgSpeed": 30.5,
    "maxSpeed": 58.2,
    "calories": 3200,
    "kudos": 45,
    "achievementCount": 6
  },
  {
    "id": 8,
    "name": "Quick Lunch Spin",
    "type": "Ride",
    "gearId": "bike-003",
    "date": "2024-01-13T12:15:00Z",
    "distance": 12.5,
    "movingTime": 1800,
    "elevation": 45,
    "avgSpeed": 25.0,
    "maxSpeed": 38.5,
    "calories": 320,
    "kudos": 3,
    "achievementCount": 0
  },
  {
    "id": 9,
    "name": "Feldberg Peak Challenge",
    "type": "Ride",
    "gearId": "bike-002",
    "date": "2024-01-07T08:00:00Z",
    "distance": 35.0,
    "movingTime": 5400,
    "elevation": 1400,
    "avgSpeed": 23.3,
    "maxSpeed": 72.1,
    "calories": 1850,
    "kudos": 56,
    "achievementCount": 8
  },
  {
    "id": 10,
    "name": "Easy Recovery Spin",
    "type": "Ride",
    "gearId": "bike-001",
    "date": "2024-01-06T10:00:00Z",
    "distance": 25.0,
    "movingTime": 3600,
    "elevation": 80,
    "avgSpeed": 25.0,
    "maxSpeed": 35.2,
    "calories": 520,
    "kudos": 4,
    "achievementCount": 0
  },
  {
    "id": 11,
    "name": "Sunday Group Ride",
    "type": "Ride",
    "gearId": "bike-001",
    "date": "2024-01-05T09:00:00Z",
    "distance": 68.0,
    "movingTime": 7800,
    "elevation": 720,
    "avgSpeed": 31.4,
    "maxSpeed": 54.6,
    "calories": 1780,
    "kudos": 28,
    "achievementCount": 2
  },
  {
    "id": 12,
    "name": "Night Ride with Lights",
    "type": "Ride",
    "gearId": "bike-003",
    "date": "2024-01-03T19:30:00Z",
    "distance": 32.0,
    "movingTime": 4200,
    "elevation": 280,
    "avgSpeed": 27.4,
    "maxSpeed": 46.8,
    "calories": 890,
    "kudos": 12,
    "achievementCount": 1
  }
]
